frametovideo/writer/__init__.py
frametovideo/writer/writer.py
frametovideo-0.0.7.dist-info/METADATA
frametovideo-0.0.7.dist-info/WHEEL
frametovideo-0.0.7.dist-info/top_level.txt
frametovideo-0.0.7.dist-info/RECORD
